{
  "metro_id": 948,
  "test_rmse": 10.418063243120173,
  "test_r_squared": 0.22033352805184925,
  "train_rmse": 10.2162703636157,
  "train_r_squared": 0.24962665965965514,
  "residual_standard_error_default": 10.418063243120173,
  "standard_error_method": "Residual SD on held-out test split by day_of_week/hour_of_day; fallback to test RMSE.",
  "standard_error_by_hour_day": [
    {
      "day_of_week": 1,
      "hour_of_day": 0,
      "standard_error": 1.7320508075688772,
      "n": 3
    },
    {
      "day_of_week": 1,
      "hour_of_day": 1,
      "standard_error": 4.79548106611445,
      "n": 35
    },
    {
      "day_of_week": 1,
      "hour_of_day": 2,
      "standard_error": 5.293924916887377,
      "n": 13
    },
    {
      "day_of_week": 1,
      "hour_of_day": 3,
      "standard_error": 5.8109092805400655,
      "n": 6
    },
    {
      "day_of_week": 1,
      "hour_of_day": 4,
      "standard_error": 15.094346150605059,
      "n": 8
    },
    {
      "day_of_week": 1,
      "hour_of_day": 5,
      "standard_error": 10.807435107127464,
      "n": 18
    },
    {
      "day_of_week": 1,
      "hour_of_day": 6,
      "standard_error": 8.063279947793175,
      "n": 14
    },
    {
      "day_of_week": 1,
      "hour_of_day": 7,
      "standard_error": 16.10442116166803,
      "n": 15
    },
    {
      "day_of_week": 1,
      "hour_of_day": 8,
      "standard_error": 5.5805785670356025,
      "n": 7
    },
    {
      "day_of_week": 1,
      "hour_of_day": 9,
      "standard_error": 12.584949438950972,
      "n": 15
    },
    {
      "day_of_week": 1,
      "hour_of_day": 10,
      "standard_error": 12.064994925987435,
      "n": 13
    },
    {
      "day_of_week": 1,
      "hour_of_day": 11,
      "standard_error": 13.016655996581202,
      "n": 10
    },
    {
      "day_of_week": 1,
      "hour_of_day": 12,
      "standard_error": 8.672148167908217,
      "n": 26
    },
    {
      "day_of_week": 1,
      "hour_of_day": 13,
      "standard_error": 10.16530045465127,
      "n": 13
    },
    {
      "day_of_week": 1,
      "hour_of_day": 14,
      "standard_error": 12.068930810518838,
      "n": 12
    },
    {
      "day_of_week": 1,
      "hour_of_day": 15,
      "standard_error": 12.86856635371633,
      "n": 21
    },
    {
      "day_of_week": 1,
      "hour_of_day": 16,
      "standard_error": 15.565321094639224,
      "n": 22
    },
    {
      "day_of_week": 1,
      "hour_of_day": 17,
      "standard_error": 11.85846333676331,
      "n": 29
    },
    {
      "day_of_week": 1,
      "hour_of_day": 18,
      "standard_error": 9.35003085145054,
      "n": 13
    },
    {
      "day_of_week": 1,
      "hour_of_day": 19,
      "standard_error": 9.565107903134512,
      "n": 42
    },
    {
      "day_of_week": 1,
      "hour_of_day": 20,
      "standard_error": 8.26650862427209,
      "n": 14
    },
    {
      "day_of_week": 1,
      "hour_of_day": 21,
      "standard_error": 5.458326972006471,
      "n": 25
    },
    {
      "day_of_week": 1,
      "hour_of_day": 22,
      "standard_error": 3.869865898059713,
      "n": 30
    },
    {
      "day_of_week": 1,
      "hour_of_day": 23,
      "standard_error": 5.391969337202627,
      "n": 25
    },
    {
      "day_of_week": 2,
      "hour_of_day": 0,
      "standard_error": 5.311263861786929,
      "n": 15
    },
    {
      "day_of_week": 2,
      "hour_of_day": 1,
      "standard_error": 1.505545305418162,
      "n": 15
    },
    {
      "day_of_week": 2,
      "hour_of_day": 3,
      "standard_error": 21.74166506963071,
      "n": 5
    },
    {
      "day_of_week": 2,
      "hour_of_day": 4,
      "standard_error": 10.512643317247546,
      "n": 27
    },
    {
      "day_of_week": 2,
      "hour_of_day": 5,
      "standard_error": 13.289093272304171,
      "n": 11
    },
    {
      "day_of_week": 2,
      "hour_of_day": 6,
      "standard_error": 11.580578066736926,
      "n": 28
    },
    {
      "day_of_week": 2,
      "hour_of_day": 7,
      "standard_error": 15.591664439693409,
      "n": 6
    },
    {
      "day_of_week": 2,
      "hour_of_day": 8,
      "standard_error": 12.817089286486919,
      "n": 10
    },
    {
      "day_of_week": 2,
      "hour_of_day": 9,
      "standard_error": 13.542877235267394,
      "n": 15
    },
    {
      "day_of_week": 2,
      "hour_of_day": 10,
      "standard_error": 15.139352694220449,
      "n": 5
    },
    {
      "day_of_week": 2,
      "hour_of_day": 11,
      "standard_error": 13.009118115775474,
      "n": 23
    },
    {
      "day_of_week": 2,
      "hour_of_day": 13,
      "standard_error": 12.919623317522328,
      "n": 16
    },
    {
      "day_of_week": 2,
      "hour_of_day": 14,
      "standard_error": 11.40175425099138,
      "n": 5
    },
    {
      "day_of_week": 2,
      "hour_of_day": 15,
      "standard_error": 11.064880430775943,
      "n": 20
    },
    {
      "day_of_week": 2,
      "hour_of_day": 16,
      "standard_error": 11.41149517908246,
      "n": 10
    },
    {
      "day_of_week": 2,
      "hour_of_day": 17,
      "standard_error": 11.35759982970106,
      "n": 29
    },
    {
      "day_of_week": 2,
      "hour_of_day": 18,
      "standard_error": 11.060402900223433,
      "n": 29
    },
    {
      "day_of_week": 2,
      "hour_of_day": 19,
      "standard_error": 6.642575518863864,
      "n": 15
    },
    {
      "day_of_week": 2,
      "hour_of_day": 20,
      "standard_error": 9.122041449787444,
      "n": 28
    },
    {
      "day_of_week": 2,
      "hour_of_day": 21,
      "standard_error": 8.557009746143015,
      "n": 42
    },
    {
      "day_of_week": 2,
      "hour_of_day": 22,
      "standard_error": 3.740766409886259,
      "n": 25
    },
    {
      "day_of_week": 2,
      "hour_of_day": 23,
      "standard_error": 3.7573457465108966,
      "n": 18
    },
    {
      "day_of_week": 3,
      "hour_of_day": 0,
      "standard_error": 0.816496580927726,
      "n": 6
    },
    {
      "day_of_week": 3,
      "hour_of_day": 1,
      "standard_error": 4.303689014140635,
      "n": 23
    },
    {
      "day_of_week": 3,
      "hour_of_day": 2,
      "standard_error": 1.4880476182856899,
      "n": 8
    },
    {
      "day_of_week": 3,
      "hour_of_day": 4,
      "standard_error": 14.337450958939668,
      "n": 16
    },
    {
      "day_of_week": 3,
      "hour_of_day": 6,
      "standard_error": 9.75320460156558,
      "n": 8
    },
    {
      "day_of_week": 3,
      "hour_of_day": 7,
      "standard_error": 7.928249671720919,
      "n": 8
    },
    {
      "day_of_week": 3,
      "hour_of_day": 8,
      "standard_error": 15.132745950421556,
      "n": 5
    },
    {
      "day_of_week": 3,
      "hour_of_day": 9,
      "standard_error": 10.681880176381126,
      "n": 13
    },
    {
      "day_of_week": 3,
      "hour_of_day": 10,
      "standard_error": 7.529703086538577,
      "n": 8
    },
    {
      "day_of_week": 3,
      "hour_of_day": 11,
      "standard_error": 13.19198891102367,
      "n": 15
    },
    {
      "day_of_week": 3,
      "hour_of_day": 12,
      "standard_error": 10.313274764284929,
      "n": 11
    },
    {
      "day_of_week": 3,
      "hour_of_day": 13,
      "standard_error": 11.152620874976087,
      "n": 15
    },
    {
      "day_of_week": 3,
      "hour_of_day": 14,
      "standard_error": 12.47397290361014,
      "n": 6
    },
    {
      "day_of_week": 3,
      "hour_of_day": 15,
      "standard_error": 16.66515144627473,
      "n": 23
    },
    {
      "day_of_week": 3,
      "hour_of_day": 17,
      "standard_error": 7.758252135015733,
      "n": 21
    },
    {
      "day_of_week": 3,
      "hour_of_day": 18,
      "standard_error": 15.535732179687392,
      "n": 13
    },
    {
      "day_of_week": 3,
      "hour_of_day": 19,
      "standard_error": 7.637746057258308,
      "n": 14
    },
    {
      "day_of_week": 3,
      "hour_of_day": 20,
      "standard_error": 7.399324293474372,
      "n": 25
    },
    {
      "day_of_week": 3,
      "hour_of_day": 21,
      "standard_error": 9.130506768309953,
      "n": 26
    },
    {
      "day_of_week": 3,
      "hour_of_day": 22,
      "standard_error": 5.1452741573065035,
      "n": 26
    },
    {
      "day_of_week": 3,
      "hour_of_day": 23,
      "standard_error": 2.8880061824976977,
      "n": 24
    },
    {
      "day_of_week": 4,
      "hour_of_day": 0,
      "standard_error": 2.265469695488437,
      "n": 17
    },
    {
      "day_of_week": 4,
      "hour_of_day": 1,
      "standard_error": 0.408248290463863,
      "n": 6
    },
    {
      "day_of_week": 4,
      "hour_of_day": 2,
      "standard_error": 0.5477225575051661,
      "n": 5
    },
    {
      "day_of_week": 4,
      "hour_of_day": 4,
      "standard_error": 10.943661922032145,
      "n": 14
    },
    {
      "day_of_week": 4,
      "hour_of_day": 5,
      "standard_error": 12.487898904444217,
      "n": 21
    },
    {
      "day_of_week": 4,
      "hour_of_day": 7,
      "standard_error": 9.377303638541932,
      "n": 17
    },
    {
      "day_of_week": 4,
      "hour_of_day": 8,
      "standard_error": 11.80442478244681,
      "n": 10
    },
    {
      "day_of_week": 4,
      "hour_of_day": 9,
      "standard_error": 12.159177119990238,
      "n": 17
    },
    {
      "day_of_week": 4,
      "hour_of_day": 10,
      "standard_error": 10.307764064044152,
      "n": 4
    },
    {
      "day_of_week": 4,
      "hour_of_day": 11,
      "standard_error": 16.408643750889034,
      "n": 13
    },
    {
      "day_of_week": 4,
      "hour_of_day": 12,
      "standard_error": 14.497184098099655,
      "n": 32
    },
    {
      "day_of_week": 4,
      "hour_of_day": 13,
      "standard_error": 12.291904209312285,
      "n": 12
    },
    {
      "day_of_week": 4,
      "hour_of_day": 15,
      "standard_error": 16.870396975698203,
      "n": 17
    },
    {
      "day_of_week": 4,
      "hour_of_day": 16,
      "standard_error": 14.418002215244243,
      "n": 12
    },
    {
      "day_of_week": 4,
      "hour_of_day": 17,
      "standard_error": 12.520277670290563,
      "n": 17
    },
    {
      "day_of_week": 4,
      "hour_of_day": 18,
      "standard_error": 9.361302629874999,
      "n": 18
    },
    {
      "day_of_week": 4,
      "hour_of_day": 19,
      "standard_error": 9.405880513556086,
      "n": 17
    },
    {
      "day_of_week": 4,
      "hour_of_day": 20,
      "standard_error": 8.990181412149692,
      "n": 27
    },
    {
      "day_of_week": 4,
      "hour_of_day": 21,
      "standard_error": 8.871029066300972,
      "n": 27
    },
    {
      "day_of_week": 4,
      "hour_of_day": 22,
      "standard_error": 4.393808775488022,
      "n": 28
    },
    {
      "day_of_week": 4,
      "hour_of_day": 23,
      "standard_error": 4.718596350097295,
      "n": 12
    },
    {
      "day_of_week": 5,
      "hour_of_day": 0,
      "standard_error": 2.5033311140691454,
      "n": 10
    },
    {
      "day_of_week": 5,
      "hour_of_day": 1,
      "standard_error": 1.0606601717798212,
      "n": 8
    },
    {
      "day_of_week": 5,
      "hour_of_day": 2,
      "standard_error": 4.949747468305833,
      "n": 2
    },
    {
      "day_of_week": 5,
      "hour_of_day": 4,
      "standard_error": 13.023455363703967,
      "n": 22
    },
    {
      "day_of_week": 5,
      "hour_of_day": 5,
      "standard_error": 7.111359122659224,
      "n": 7
    },
    {
      "day_of_week": 5,
      "hour_of_day": 6,
      "standard_error": 13.173973258989538,
      "n": 8
    },
    {
      "day_of_week": 5,
      "hour_of_day": 7,
      "standard_error": 3.8078865529319543,
      "n": 5
    },
    {
      "day_of_week": 5,
      "hour_of_day": 8,
      "standard_error": 15.250194131637524,
      "n": 20
    },
    {
      "day_of_week": 5,
      "hour_of_day": 9,
      "standard_error": 11.765878523760879,
      "n": 13
    },
    {
      "day_of_week": 5,
      "hour_of_day": 10,
      "standard_error": 7.758865896508329,
      "n": 5
    },
    {
      "day_of_week": 5,
      "hour_of_day": 11,
      "standard_error": 11.234814312287451,
      "n": 20
    },
    {
      "day_of_week": 5,
      "hour_of_day": 12,
      "standard_error": 3.7682887362833544,
      "n": 5
    },
    {
      "day_of_week": 5,
      "hour_of_day": 13,
      "standard_error": 12.802675374000003,
      "n": 18
    },
    {
      "day_of_week": 5,
      "hour_of_day": 14,
      "standard_error": 9.85900603509299,
      "n": 31
    },
    {
      "day_of_week": 5,
      "hour_of_day": 15,
      "standard_error": 9.690201236300513,
      "n": 6
    },
    {
      "day_of_week": 5,
      "hour_of_day": 16,
      "standard_error": 12.0048361902203,
      "n": 30
    },
    {
      "day_of_week": 5,
      "hour_of_day": 17,
      "standard_error": 12.773484440899624,
      "n": 21
    },
    {
      "day_of_week": 5,
      "hour_of_day": 18,
      "standard_error": 14.428831431220903,
      "n": 17
    },
    {
      "day_of_week": 5,
      "hour_of_day": 19,
      "standard_error": 9.75,
      "n": 16
    },
    {
      "day_of_week": 5,
      "hour_of_day": 20,
      "standard_error": 11.027239001672177,
      "n": 31
    },
    {
      "day_of_week": 5,
      "hour_of_day": 21,
      "standard_error": 10.570714261581381,
      "n": 25
    },
    {
      "day_of_week": 5,
      "hour_of_day": 22,
      "standard_error": 8.35883543743564,
      "n": 22
    },
    {
      "day_of_week": 5,
      "hour_of_day": 23,
      "standard_error": 7.361344574151785,
      "n": 33
    },
    {
      "day_of_week": 6,
      "hour_of_day": 0,
      "standard_error": 3.735288603626359,
      "n": 15
    },
    {
      "day_of_week": 6,
      "hour_of_day": 1,
      "standard_error": 2.7141603981096374,
      "n": 6
    },
    {
      "day_of_week": 6,
      "hour_of_day": 2,
      "standard_error": 3.283201450521409,
      "n": 17
    },
    {
      "day_of_week": 6,
      "hour_of_day": 3,
      "standard_error": 9.118270512704543,
      "n": 7
    },
    {
      "day_of_week": 6,
      "hour_of_day": 4,
      "standard_error": 7.841586331251871,
      "n": 21
    },
    {
      "day_of_week": 6,
      "hour_of_day": 5,
      "standard_error": 11.29527924990495,
      "n": 4
    },
    {
      "day_of_week": 6,
      "hour_of_day": 6,
      "standard_error": 8.512089345432797,
      "n": 29
    },
    {
      "day_of_week": 6,
      "hour_of_day": 7,
      "standard_error": 3.055050463303893,
      "n": 3
    },
    {
      "day_of_week": 6,
      "hour_of_day": 8,
      "standard_error": 10.23955491456952,
      "n": 22
    },
    {
      "day_of_week": 6,
      "hour_of_day": 9,
      "standard_error": 11.845940899290088,
      "n": 20
    },
    {
      "day_of_week": 6,
      "hour_of_day": 10,
      "standard_error": 11.623606372732393,
      "n": 22
    },
    {
      "day_of_week": 6,
      "hour_of_day": 11,
      "standard_error": 14.343460129440471,
      "n": 33
    },
    {
      "day_of_week": 6,
      "hour_of_day": 12,
      "standard_error": 13.157293759925226,
      "n": 18
    },
    {
      "day_of_week": 6,
      "hour_of_day": 13,
      "standard_error": 13.750998039776862,
      "n": 28
    },
    {
      "day_of_week": 6,
      "hour_of_day": 14,
      "standard_error": 12.57694268013841,
      "n": 27
    },
    {
      "day_of_week": 6,
      "hour_of_day": 15,
      "standard_error": 12.383243894260072,
      "n": 27
    },
    {
      "day_of_week": 6,
      "hour_of_day": 16,
      "standard_error": 12.389074924673652,
      "n": 22
    },
    {
      "day_of_week": 6,
      "hour_of_day": 17,
      "standard_error": 12.135108963879038,
      "n": 23
    },
    {
      "day_of_week": 6,
      "hour_of_day": 18,
      "standard_error": 11.091230076749136,
      "n": 26
    },
    {
      "day_of_week": 6,
      "hour_of_day": 19,
      "standard_error": 9.995542678628569,
      "n": 34
    },
    {
      "day_of_week": 6,
      "hour_of_day": 20,
      "standard_error": 10.524318995668112,
      "n": 31
    },
    {
      "day_of_week": 6,
      "hour_of_day": 21,
      "standard_error": 11.805163919289317,
      "n": 32
    },
    {
      "day_of_week": 6,
      "hour_of_day": 22,
      "standard_error": 10.934614280974166,
      "n": 20
    },
    {
      "day_of_week": 6,
      "hour_of_day": 23,
      "standard_error": 8.543307043416808,
      "n": 28
    },
    {
      "day_of_week": 7,
      "hour_of_day": 0,
      "standard_error": 6.3420069876639955,
      "n": 20
    },
    {
      "day_of_week": 7,
      "hour_of_day": 1,
      "standard_error": 4.555216789572149,
      "n": 9
    },
    {
      "day_of_week": 7,
      "hour_of_day": 2,
      "standard_error": 4.988407614290936,
      "n": 20
    },
    {
      "day_of_week": 7,
      "hour_of_day": 3,
      "standard_error": 5.385164807134504,
      "n": 5
    },
    {
      "day_of_week": 7,
      "hour_of_day": 4,
      "standard_error": 4.712879156791957,
      "n": 34
    },
    {
      "day_of_week": 7,
      "hour_of_day": 5,
      "standard_error": 1.7320508075688772,
      "n": 3
    },
    {
      "day_of_week": 7,
      "hour_of_day": 6,
      "standard_error": 8.375417544673164,
      "n": 21
    },
    {
      "day_of_week": 7,
      "hour_of_day": 7,
      "standard_error": 5.656854249492381,
      "n": 2
    },
    {
      "day_of_week": 7,
      "hour_of_day": 8,
      "standard_error": 8.762359691796556,
      "n": 20
    },
    {
      "day_of_week": 7,
      "hour_of_day": 9,
      "standard_error": 11.03815696078422,
      "n": 12
    },
    {
      "day_of_week": 7,
      "hour_of_day": 10,
      "standard_error": 13.292216012988492,
      "n": 18
    },
    {
      "day_of_week": 7,
      "hour_of_day": 11,
      "standard_error": 12.653245251105163,
      "n": 26
    },
    {
      "day_of_week": 7,
      "hour_of_day": 12,
      "standard_error": 10.613109593238695,
      "n": 15
    },
    {
      "day_of_week": 7,
      "hour_of_day": 13,
      "standard_error": 12.210342874722217,
      "n": 31
    },
    {
      "day_of_week": 7,
      "hour_of_day": 14,
      "standard_error": 12.888358637149587,
      "n": 28
    },
    {
      "day_of_week": 7,
      "hour_of_day": 15,
      "standard_error": 14.005072133143244,
      "n": 33
    },
    {
      "day_of_week": 7,
      "hour_of_day": 16,
      "standard_error": 10.332757280410345,
      "n": 28
    },
    {
      "day_of_week": 7,
      "hour_of_day": 17,
      "standard_error": 13.100687928255843,
      "n": 32
    },
    {
      "day_of_week": 7,
      "hour_of_day": 18,
      "standard_error": 11.880957152399079,
      "n": 21
    },
    {
      "day_of_week": 7,
      "hour_of_day": 19,
      "standard_error": 9.207077183898821,
      "n": 37
    },
    {
      "day_of_week": 7,
      "hour_of_day": 20,
      "standard_error": 8.512576811046346,
      "n": 37
    },
    {
      "day_of_week": 7,
      "hour_of_day": 21,
      "standard_error": 8.701254389856054,
      "n": 31
    },
    {
      "day_of_week": 7,
      "hour_of_day": 22,
      "standard_error": 3.884646211751617,
      "n": 21
    },
    {
      "day_of_week": 7,
      "hour_of_day": 23,
      "standard_error": 4.716699348829937,
      "n": 14
    }
  ]
}